anchorscad/LICENSE
anchorscad/__init__.py
anchorscad/ad_viewer.py
anchorscad/core.py
anchorscad/examples_monitor.py
anchorscad/extrude.py
anchorscad/extrude_flex.py
anchorscad/fabricate_lib.py
anchorscad/fabricate_runner.py
anchorscad/graph_model.py
anchorscad/path_mesh.py
anchorscad/path_ops.py
anchorscad/path_utils.py
anchorscad/renderer.py
anchorscad/svg_renderer.py
anchorscad/template.py
anchorscad/template_with_dt_node.py
anchorscad/template_with_extrusion.py
anchorscad/zero_finder.py
anchorscad/fab/__init__.py
anchorscad/fab/config/__init__.py
anchorscad/fab/config/printers/__init__.py
anchorscad/fab/config/printers/printer_volume.py
anchorscad/fab/config/printers/printers.py
anchorscad/fab/config/printers/bambu/__init__.py
anchorscad/fab/config/printers/bambu/fdm.py
anchorscad/fab/config/printers/prusa/__init__.py
anchorscad/fab/config/printers/prusa/fdm.py
anchorscad/fab/config/slicers/__init__.py
anchorscad/runner/__init__.py
anchorscad/runner/anchorscad_runner.py
anchorscad/runner/compare_generated.py
anchorscad/runner/diff_viewer.html
anchorscad/runner/runner_status.py
anchorscad/webpage/animators.js
anchorscad/webpage/generated_viewer.html
anchorscad/webpage/interpolators.js
anchorscad/webpage/viewer5.html
anchorscad/webpage/webpage_server.py
anchorscad_models/basic/SquarePipe.py
anchorscad_models/basic/TriangularPrism.py
anchorscad_models/basic/__init__.py
anchorscad_models/basic/angle_extrusion.py
anchorscad_models/basic/box_cylinder.py
anchorscad_models/basic/box_side_bevels.py
anchorscad_models/basic/cone_ended_prism.py
anchorscad_models/basic/extruded_sequence.py
anchorscad_models/basic/parallelogram_rounded.py
anchorscad_models/basic/pipe.py
anchorscad_models/basic/poly_conical.py
anchorscad_models/basic/regular_prism.py
anchorscad_models/basic/sleeve.py
anchorscad_models/basic/sphere_section.py
anchorscad_models/basic/spherical_cap.py
anchorscad_models/basic/stadium.py
anchorscad_models/basic/torus.py
anchorscad_models/basic/trapezoid_prism.py
anchorscad_core-0.2.4.dist-info/METADATA
anchorscad_core-0.2.4.dist-info/WHEEL
anchorscad_core-0.2.4.dist-info/RECORD
