Metadata-Version: 2.4
Name: anchorscad-core
Version: 0.2.4
Summary: A Python 3D modelling API for generating OpenSCAD source code. This library simplifies the creating of 3D models. This contains only the core API and some generic basic models.
Project-URL: Homepage, https://github.com/owebeeone/anchorscad-core
Project-URL: Bug Tracker, https://github.com/owebeeone/anchorscad-core/issues
Author-email: Gianni Mariani <gianni@mariani.ws>
Classifier: License :: OSI Approved :: GNU Lesser General Public License v2 or later (LGPLv2+)
Classifier: Operating System :: OS Independent
Classifier: Programming Language :: Python :: 3
Requires-Python: >=3.10
Requires-Dist: anchorscad-linear>=0.1.1
Requires-Dist: anchorscad-test-tools>=0.1.0
Requires-Dist: anchorscad-utils>=0.1.1
Requires-Dist: dataclasses-json
Requires-Dist: datatrees>=0.3.1
Requires-Dist: debugpy
Requires-Dist: dill
Requires-Dist: frozendict
Requires-Dist: graphviz
Requires-Dist: lxml
Requires-Dist: matplotlib
Requires-Dist: numpy
Requires-Dist: numpy-stl
Requires-Dist: pillow
Requires-Dist: pythonopenscad>=2.2.19
Requires-Dist: sortedcollections
Requires-Dist: sortedcontainers
Requires-Dist: svgelements
Requires-Dist: svgpathtools
Requires-Dist: to-3mf
Requires-Dist: xdatatrees>=0.1.0
